psychopy_bids/__init__.py
psychopy_bids/bids/__init__.py
psychopy_bids/bids/bidsbehevent.py
psychopy_bids/bids/bidserror.py
psychopy_bids/bids/bidshandler.py
psychopy_bids/bids/bidstaskevent.py
psychopy_bids/bids/template/README
psychopy_bids/bids/template/dataset_description.json
psychopy_bids/bids/template/participants.json
psychopy_bids/bids_event/__init__.py
psychopy_bids/bids_event/classic/BIDS.png
psychopy_bids/bids_event/dark/BIDS.png
psychopy_bids/bids_event/dark/BIDS@2x.png
psychopy_bids/bids_event/light/BIDS.png
psychopy_bids/bids_event/light/BIDS@2x.png
psychopy_bids/bids_settings/__init__.py
psychopy_bids/bids_settings/classic/BIDS.png
psychopy_bids/bids_settings/dark/BIDS.png
psychopy_bids/bids_settings/dark/BIDS@2x.png
psychopy_bids/bids_settings/light/BIDS.png
psychopy_bids/bids_settings/light/BIDS@2x.png
psychopy_bids/deprecated/bids_beh/__init__.py
psychopy_bids/deprecated/bids_beh/classic/BIDS.png
psychopy_bids/deprecated/bids_beh/dark/BIDS.png
psychopy_bids/deprecated/bids_beh/dark/BIDS@2x.png
psychopy_bids/deprecated/bids_beh/light/BIDS.png
psychopy_bids/deprecated/bids_beh/light/BIDS@2x.png
psychopy_bids/deprecated/bids_task/__init__.py
psychopy_bids/deprecated/bids_task/classic/BIDS.png
psychopy_bids/deprecated/bids_task/dark/BIDS.png
psychopy_bids/deprecated/bids_task/dark/BIDS@2x.png
psychopy_bids/deprecated/bids_task/light/BIDS.png
psychopy_bids/deprecated/bids_task/light/BIDS@2x.png
psychopy_bids-2025.1.2.dist-info/LICENSE
psychopy_bids-2025.1.2.dist-info/METADATA
psychopy_bids-2025.1.2.dist-info/WHEEL
psychopy_bids-2025.1.2.dist-info/entry_points.txt
psychopy_bids-2025.1.2.dist-info/top_level.txt
psychopy_bids-2025.1.2.dist-info/RECORD
