Metadata-Version: 2.2
Name: psychopy-bids
Version: 2025.1.2
Summary: A PsychoPy plugin for using the Brain Imaging Data Structure (BIDS) to organize and describe data.
Author-email: Christoph Anzengruber <christoph.anzengruber@uni-graz.at>, Florian Schöngaßner <florian.schoengassner@uni-graz.at>
Maintainer-email: Lukas Wiertz <lukas.wiertz@uni-graz.at>
License: GNU General Public License v3 (GPLv3)
Project-URL: homepage, https://psygraz.gitlab.io/psychopy-bids
Project-URL: project, https://pypi.org/project/psychopy-bids
Project-URL: changelog, https://gitlab.com/psygraz/psychopy-bids/-/blob/master/CHANGELOG.md
Project-URL: documentation, https://psychopy-bids.readthedocs.io/en/stable
Project-URL: repository, https://gitlab.com/psygraz/psychopy-bids
Keywords: psychopy,bids,psychology,data organization
Classifier: License :: OSI Approved :: GNU General Public License v3 (GPLv3)
Classifier: Programming Language :: Python :: 3
Classifier: Programming Language :: Python :: 3 :: Only
Classifier: Programming Language :: Python :: 3.8
Classifier: Programming Language :: Python :: 3.9
Classifier: Programming Language :: Python :: 3.10
Classifier: Programming Language :: Python :: Implementation :: CPython
Requires-Python: >=3.8
License-File: LICENSE
Requires-Dist: requests>=2.31.0
Requires-Dist: numpy>=1.21.0
Requires-Dist: pandas>=1.4.3
Requires-Dist: hedtools>=0.5.0
Requires-Dist: packaging>=20.0
Provides-Extra: docs
Requires-Dist: mkdocs; extra == "docs"
Requires-Dist: mkdocs-material; extra == "docs"
Requires-Dist: mkdocstrings; extra == "docs"
Requires-Dist: mkdocstrings-python; extra == "docs"
Requires-Dist: mkdocs-jupyter; extra == "docs"
Requires-Dist: mkdocs-roamlinks-plugin; extra == "docs"
Requires-Dist: seedir; extra == "docs"
Requires-Dist: pytkdocs[numpy-style]; extra == "docs"
Provides-Extra: dev
Requires-Dist: autopep8; extra == "dev"
Requires-Dist: black; extra == "dev"
Requires-Dist: isort; extra == "dev"
Requires-Dist: bandit; extra == "dev"
Requires-Dist: codespell; extra == "dev"
Requires-Dist: flake8; extra == "dev"
Requires-Dist: pylint; extra == "dev"
Requires-Dist: pytest-cov; extra == "dev"
Requires-Dist: pytest; extra == "dev"
Requires-Dist: psychopy; extra == "dev"
